structured_data/__init__.py
structured_data/_attribute_constructor.py
structured_data/_cant_modify.py
structured_data/_conditional_method.py
structured_data/_doc_wrapper.py
structured_data/_nillable_write.py
structured_data/_not_in.py
structured_data/_pep_570_when.py
structured_data/_stack_iter.py
structured_data/_unpack.py
structured_data/adt.py
structured_data/data.py
structured_data/match.py
structured_data/py.typed
structured_data/_adt/__init__.py
structured_data/_adt/annotations.py
structured_data/_adt/constructor.py
structured_data/_adt/ctor.py
structured_data/_adt/ordering.py
structured_data/_adt/prewritten_methods.py
structured_data/_adt/product_type.py
structured_data/_adt/sum_type.py
structured_data/_match/__init__.py
structured_data/_match/destructure.py
structured_data/_match/match_dict.py
structured_data/_match/match_failure.py
structured_data/_match/matchable.py
structured_data/_match/descriptor/__init__.py
structured_data/_match/descriptor/common.py
structured_data/_match/descriptor/function.py
structured_data/_match/descriptor/property_.py
structured_data/_match/patterns/__init__.py
structured_data/_match/patterns/basic_patterns.py
structured_data/_match/patterns/bind.py
structured_data/_match/patterns/compound_match.py
structured_data/_match/patterns/mapping_match.py
structured_data-0.13.0.dist-info/AUTHORS.rst
structured_data-0.13.0.dist-info/LICENSE
structured_data-0.13.0.dist-info/METADATA
structured_data-0.13.0.dist-info/WHEEL
structured_data-0.13.0.dist-info/top_level.txt
structured_data-0.13.0.dist-info/RECORD
