Metadata-Version: 2.1
Name: structured-data
Version: 0.13.0
Summary: Code generators for immutable structured data, including algebraic data types, and functions to destructure them.
Home-page: https://github.com/mwchase/python-structured-data
Author: Max Woerner Chase
Author-email: max.chase@gmail.com
License: MIT license
Platform: UNKNOWN
Classifier: Development Status :: 5 - Production/Stable
Classifier: Intended Audience :: Developers
Classifier: License :: OSI Approved :: MIT License
Classifier: Operating System :: Unix
Classifier: Operating System :: POSIX
Classifier: Operating System :: Microsoft :: Windows
Classifier: Programming Language :: Python
Classifier: Programming Language :: Python :: 3
Classifier: Programming Language :: Python :: 3.7
Classifier: Programming Language :: Python :: Implementation :: CPython
Classifier: Topic :: Utilities
Requires-Python: >=3.7
Requires-Dist: astor
